ics_sbom_libs/__init__.py
ics_sbom_libs/common/__init__.py
ics_sbom_libs/common/console_output.py
ics_sbom_libs/common/dbproperties.py
ics_sbom_libs/common/logging_setup.py
ics_sbom_libs/common/ratelimiter.py
ics_sbom_libs/common/tests/test_dbproperties.py
ics_sbom_libs/common/tests/test_logging_setup.py
ics_sbom_libs/common/vulnerability.py
ics_sbom_libs/cve_fetch/__init__.py
ics_sbom_libs/cve_fetch/cve_schema.sql
ics_sbom_libs/cve_fetch/vulnerabilitydatabase.py
ics_sbom_libs/cve_match/__init__.py
ics_sbom_libs/cve_match/cpe_match_results.py
ics_sbom_libs/cve_match/cvematcher.py
ics_sbom_libs/cve_match/matchresult.py
ics_sbom_libs/cve_match/package_matching/__init__.py
ics_sbom_libs/cve_match/package_matching/base.py
ics_sbom_libs/cve_match/package_matching/buildversion.py
ics_sbom_libs/cve_match/package_matching/handlers/__init__.py
ics_sbom_libs/cve_match/package_matching/handlers/default.py
ics_sbom_libs/cve_match/package_matching/handlers/linux_kernel.py
ics_sbom_libs/cve_match/package_matching/handlers/openssh.py
ics_sbom_libs/cve_match/package_matching/handlers/openssl.py
ics_sbom_libs/cve_match/package_matching/versionfactory.py
ics_sbom_libs/sbom_import/FilterSpec.md
ics_sbom_libs/sbom_import/__init__.py
ics_sbom_libs/sbom_import/filter_schema.json
ics_sbom_libs/sbom_import/parse_anything.py
ics_sbom_libs/sbom_import/spdx_json/__init__.py
ics_sbom_libs/sbom_import/spdx_json/parse.py
ics_sbom_libs/sbom_import/spdx_tag_value/__init__.py
ics_sbom_libs/sbom_import/spdx_tag_value/filter_lexers.py
ics_sbom_libs/sbom_import/spdx_tag_value/parse.py
ics_sbom_libs/sbom_import/spdx_tag_value/progress_lexer.py
ics_sbom_libs-1.3.0.dist-info/COPYING.txt
ics_sbom_libs-1.3.0.dist-info/LICENSES/CC-BY-SA-4.0.txt
ics_sbom_libs-1.3.0.dist-info/LICENSES/LGPL-2.0-or-later.txt
ics_sbom_libs-1.3.0.dist-info/LICENSES/MIT.txt
ics_sbom_libs-1.3.0.dist-info/METADATA
ics_sbom_libs-1.3.0.dist-info/WHEEL
ics_sbom_libs-1.3.0.dist-info/RECORD
