Metadata-Version: 2.3
Name: ics_sbom_libs
Version: 1.3.0
Summary: ICS SBoM libs is a set of libraries developed by Integrated Computer Solutions (ICS) for handling Software Bill of Materials (SBoM) documentaion.
Author: Michael Dingwall
Author-email: mdingwall@ics.com
Requires-Python: >=3.9,<4.0
Classifier: Programming Language :: Python :: 3
Classifier: Programming Language :: Python :: 3.9
Classifier: Programming Language :: Python :: 3.10
Classifier: Programming Language :: Python :: 3.11
Classifier: Programming Language :: Python :: 3.12
Classifier: Programming Language :: Python :: 3.13
Requires-Dist: aiohttp
Requires-Dist: backports-zstd ; python_version < "3.14"
Requires-Dist: cpeparser
Requires-Dist: cyclonedx-python-lib[validation] (>=7.3.0)
Requires-Dist: datetime
Requires-Dist: lib4sbom
Requires-Dist: psycopg2-binary
Requires-Dist: pyodbc
Requires-Dist: requests
Requires-Dist: rich
Requires-Dist: rich-argparse
Requires-Dist: schema
Requires-Dist: spdx-tools
Requires-Dist: tqdm
Requires-Dist: xmlschema
